{"py/object": "rasa.core.featurizers.tracker_featurizers.MaxHistoryTrackerFeaturizer", "state_featurizer": {"py/object": "rasa.core.featurizers.single_state_featurizer.SingleStateFeaturizer", "_default_feature_states": {"intent": {"back": 0, "nlu_fallback": 1, "out_of_scope": 2, "proporcionar_correo": 3, "proporcionar_edad": 4, "proporcionar_estudias": 5, "proporcionar_horario": 6, "proporcionar_nacimiento": 7, "proporcionar_nombre": 8, "proporcionar_telefono": 9, "respuesta_opcion_1": 10, "respuesta_opcion_2": 11, "respuesta_opcion_3": 12, "restart": 13, "saludo_opciones": 14, "session_start": 15}, "action_name": {"action_listen": 0, "action_restart": 1, "action_session_start": 2, "action_default_fallback": 3, "action_deactivate_loop": 4, "action_revert_fallback_events": 5, "action_default_ask_affirmation": 6, "action_default_ask_rephrase": 7, "action_two_stage_fallback": 8, "action_unlikely_intent": 9, "action_back": 10, "...": 11, "action_extract_slots": 12, "utter_respuesta_opcion_1_telefono": 13, "utter_respuesta_opcion_1_correo": 14, "utter_saludo_opciones": 15, "utter_respuesta_opcion_1_nombre": 16, "utter_respuesta_opcion_1": 17, "utter_respuesta_opcion_1_edad": 18, "utter_respuesta_opcion_1_nacimiento": 19, "utter_respuesta_opcion_1_horario": 20, "utter_respuesta_opcion_2": 21, "utter_respuesta_opcion_3": 22, "utter_respuesta_opcion_1_estudias": 23}, "entities": {"correo": 0, "edad": 1, "estudias": 2, "horario": 3, "nacimiento": 4, "nombre": 5, "telefono": 6}, "slots": {}, "active_loop": {}}, "action_texts": [], "entity_tag_specs": []}, "max_history": 5, "remove_duplicates": true}